Workbook

Sheet Instrucoes
A1: COMO USAR ESTA PLANILHA
A3: Células AMARELAS | B3: São os valores que você digita todo mês (líquidos, IRRF, valores de consignações, saldos de empenho). O resto é calculado automaticamente por fórmula.
A4: Células sem cor / com fórmula | B4: Não edite. Estão protegidas — se tentar mexer, o Sheets vai avisar antes.
A5: Códigos orçamentários (ex: 31.90.11.74) | B5: Veja o significado de cada um na aba "Glossario de Codigos".
A6: Aba "Cruzamento Rubricas" | B6: Os rótulos das linhas 2 a 8 foram deduzidos automaticamente cruzando valores — passe o mouse sobre a coluna A para ver a explicação e o nível de confiança.
A8: LANÇAR A FOLHA DE UM NOVO MÊS
B9: Use o menu FOPAG > "Lançar novo mês" no topo da tela. Isso cria uma cópia completa desta planilha (fórmulas e proteções inclusas), já com as células amarelas em branco, pronta para você preencher.
B10: O arquivo do mês atual não é apagado nem sobrescrito — cada mês fica com seu próprio arquivo no Google Drive.

Sheet Dashboard
A1: DASHBOARD FOPAG | T1: DADOS AUXILIARES - NÃO EDITAR
A2: ='LÍQUIDO FOLHA -1'!A3 -> LIQUIDAÇÃO DA FOLHA DE PAGAMENTO DO MÊS DE JULHO DE 2026-1 | T2: Regime | U2: Líquido
T3: ='CONSIGNAÇÕES FOLHA 1'!A3 -> LÍQUIDO DOS CONTRATOS | U3: ='CONSIGNAÇÕES FOLHA 1'!D3 -> 68692.72
B4: VALOR DA FOPAG (TOTAL DO MÊS) | E4: TOTAL LÍQUIDO (TODOS OS REGIMES) | H4: TOTAL IRRF RETIDO | K4: TOTAL DE CONSIGNAÇÕES | N4: ENCARGOS SOCIAIS (FUNDOS+INSS+PLANSAUDE) | T4: ='CONSIGNAÇÕES FOLHA 1'!A4 -> LÍQUIDO VENCIMENTO PESSOAL CIVIL RPPS | U4: ='CONSIGNAÇÕES FOLHA 1'!D4 -> 128490.03
B5: ='LÍQUIDO FOLHA -1'!F79 -> 694407.63 | E5: ='CONSIGNAÇÕES FOLHA 1'!D7 -> 471029.4 | H5: =SUM('LÍQUIDO FOLHA -1'!I15,'LÍQUIDO FOLHA -1'!I30,'LÍQUIDO FOLHA -1'!I44,'LÍQUIDO FOLHA -1'!I58) -> #ERROR! | K5: =SUM('CONSIGNAÇÕES FOLHA 1'!F14:J97) -> 119657.39 | N5: =SUM('LÍQUIDO FOLHA -1'!F68:F76) -> 104222.85 | T5: ='CONSIGNAÇÕES FOLHA 1'!A5 -> LÍQUIDO DO SUBSÍDIO RGPS | U5: ='CONSIGNAÇÕES FOLHA 1'!D5 -> 257926.4
A6: ="Diferença apurada na aba Reconciliação: " & TEXT('Reconciliacao'!B23,"R$ #,##0.00") & " — confira se esse valor é esperado (ex: RGPS/Militar fora do escopo daquela aba) antes de tratar como erro." -> #ERROR! | T6: ='CONSIGNAÇÕES FOLHA 1'!A6 -> LIQUIDO PESSOAL MILITAR | U6: ='CONSIGNAÇÕES FOLHA 1'!D6 -> 15920.25
T9: Categoria | U9: Valor
T10: Valor do Órgão para Empenho | U10: ='LÍQUIDO FOLHA -1'!F67 -> 590184.78
T11: Encargos Sociais | U11: =SUM('LÍQUIDO FOLHA -1'!F68:F76) -> 104222.85
T14: Encargo | U14: Valor
T15: ='LÍQUIDO FOLHA -1'!G68 -> FUNDO FINANCEIRO | U15: ='LÍQUIDO FOLHA -1'!F68 -> 24685.86
T16: ='LÍQUIDO FOLHA -1'!G69 -> FUNDO PREVIDENCIÁRIO | U16: ='LÍQUIDO FOLHA -1'!F69 -> 4503.31
T17: ='LÍQUIDO FOLHA -1'!G70 -> INSS | U17: ='LÍQUIDO FOLHA -1'!F70 -> 68775.92
T18: ='LÍQUIDO FOLHA -1'!G71 -> PLANSAUDE | U18: ='LÍQUIDO FOLHA -1'!F71 -> 6257.76
T20: Instituição | U20: Total (R$)
T21: =QUERY({'CONSIGNAÇÕES FOLHA 1'!E14:E97, 'CONSIGNAÇÕES FOLHA 1'!F14:F97+'CONSIGNAÇÕES FOLHA 1'!G14:G97+'CONSIGNAÇÕES FOLHA 1'!H14:H97+'CONSIGNAÇÕES FOLHA 1'!I14:I97+'CONSIGNAÇÕES FOLHA 1'!J14:J97}, "select Col1, Col2 where Col2 > 0 order by Col2 desc limit 10", 0) -> #ERROR!
T34: Rubrica (NES) | U34: Valor do Reforço (R$)
T35: =QUERY({NES!C2:C23, NES!G2:G23}, "select Col1, Col2 where Col2 > 0 order by Col2 desc limit 8", 0) -> #ERROR!
T44: Categoria | U44: Valor
T45: Líquido Total | U45: ='CONSIGNAÇÕES FOLHA 1'!D7 -> 471029.4
T46: Consignações Total | U46: =SUM('CONSIGNAÇÕES FOLHA 1'!F14:J97) -> 119657.39
T47: IRRF Total | U47: =SUM('LÍQUIDO FOLHA -1'!I15,'LÍQUIDO FOLHA -1'!I30,'LÍQUIDO FOLHA -1'!I44,'LÍQUIDO FOLHA -1'!I58) -> #ERROR!
T48: Encargos Sociais | U48: =SUM('LÍQUIDO FOLHA -1'!F68:F76) -> 104222.85

Sheet LÍQUIDO FOLHA -1
A1: PROCESSO: 2026/093010/000015 DATA ABERTURA: 21/07/2026 | F1: ULTIMA VERSÃO
A3: LIQUIDAÇÃO DA FOLHA DE PAGAMENTO DO MÊS DE JULHO DE 2026-1
D4: CONTRATOS - RGPS
A5: EVENTO | B5: NE | C5: NATUREZA | D5: RUBRICA | E5: CLASSIFICAÇÃO PAGAMENTO | F5: DESCRIÇÃO | G5: LÍQUIDO | H5: LIQUIDAÇÃO | I5: IRRF
C6: 3.31.90.04.01 | F6: Despesas Remuneração e IRRF última coluna | G6: 65892.72 | H6: =G6:G7-H7-H8-H10-H9-H12+G13+G11 -> 63167.72 | I6: 0
C7: 3.31.90.04.02 | F7: 13° Contratos e Adiantamento 13º | G7: 225 | H7: =G7 -> 225
C8: 3.31.90.13.02 | F8: Salario maternidade - INSS | G8: 0 | H8: =G8 -> 0
C9: 3.31.90.04.45 | F9: Férias Proporcionais Indenizadas | G9: 0 | H9: 0
C10: 3.31.90.04.02 | F10: Salário família INSS Contratos | G10: 0 | H10: =G10 -> 0
C11: 3.31.90.92.04 | F11: Contratos (Desp. Anterior) DEA | G11: 0
C12: 3.33.90.46 | D12: 3645 | F12: Auxílio Alimentação contratos | G12: 2500 | H12: =G12 -> 2500
B13: AJ3000005 | C13: 33.90.92 | D13: _ | E13: _ | F13: Rendimentos- Exercício anterior DEA | G13: 0 | H13: 0
C14: 3.31.90.94.01 | D14: NÃO EXIGE | E14: 211110101 | F14: Contratos Indenizações | G14: 2800 | H14: =G14 -> 2800
B15: _ | C15: _ | D15: 211.110.10X | F15: , | H15: 68692.72 | I15: =SUM(I6:I14) -> 0
D16: RPPS
A17: EVENTO | B17: NE | C17: NATUREZA | D17: RUBRICA | E17: CLASSIFICAÇÃO PAGAMENTO | F17: DESCRIÇÃO | G17: LÍQUIDO | H17: LIQUIDAÇÃO | I17: IRRF
C18: 3.31.90.05.07 | F18: Salário Familia Civil RPPS | G18: 0 | H18: =G18 -> 0 | I18: 0
C19: 3.31.90.11.43 | F19: 13° Salário Civil RPPS | G19: 32736.28 | H19: =G19 -> 32736.28
C20: 31.90.11.07 | F20: Abono permanência | G20: 0 | H20: =G20 -> 0 | I20: 0
C21: 31.90.11.07 | F21: Abono permanência 13º | G21: 0 | H21: 0
C22: 3.31.90.11.45 | F22: Férias Abono/Adicional de férias Const. Civil RPPS | G22: 113.59 | H22: =G22 -> 113.59
C23: 3.33.90.46 | D23: 3645 | F23: Auxílio Alimentação RPPS | G23: 0 | H23: =G23 -> 0
C24: 3.33.90.93.02 | F24: Ressarcimento 30%, Art. 22-B, MP 03/2024. | G24: 5172.33 | H24: =G24 -> 5172.33
C25: 3.33.90.93.02 | F25: Ressarcimento 40% Art.22-A | G25: 15935.28 | H25: =G25 -> 15935.28
C26: 3.31.90.92.11 | F26: Vencimento P. Civil (exerc. Anterior) DEA folha banco | G26: 5448.82 | H26: =G26 -> 5448.82 | I26: 0
C27: 3.31.90.11.74 | F27: Subsídios Civil RPPS (folha 1) | G27: 28173.56 | H27: =G27 -> 28173.56 | I27: 0
C28: 3.31.90.11.01 | F28: VENCIMENTO DE P. CIVIL e IRRF folha banco e ultima coluna | G28: 95035.04 | H28: =G28-(H19+H22+H25+H27+H20+H21+H23+H24) -> 12904 | I28: 21954.09
C29: 3.31.90.94.01 | F29: Venc. P. Civil. (indenizações) folha banco | G29: 28006.17 | H29: 28006.17
B30: _ | D30: 211.110.10X | E30: _ | F30: LÍQUIDO | H30: 128490.03 | I30: =SUM(I18:I29) -> 21954.09
D31: RGPS
A32: EVENTO | B32: NE | C32: NATUREZA | D32: RUBRICA | E32: CLASSIFICAÇÃO PAGAMENTO | F32: DESCRIÇÃO | G32: LÍQUIDO | H32: LIQUIDAÇÃO | I32: IRRF
C33: 3.31.90.11.43 | F33: 13° e Adiantamento Salário Civil RGPS | G33: 17777.97 | H33: =G33 -> 17777.97 | I33: 0
C34: 3.31.90.11.45 | F34: Férias Abono Const. Civil RGPS | G34: 0 | H34: =G34 -> 0
C35: 3.31.90.11.74 | F35: Subsídios Civil RPPS (folha banco) + IRRF ultima coluna | G35: 208034.53 | H35: =G35-H33-H39-H34-H40-H37-H42-H38 -> 140364.69 | I35: 15363.42
C36: 3.31.90.11.01 | F36: VENCIMENTO PESSOAL CIVIL | G36: 0 | H36: 0 | I36: 0
C37: 3.33.90.93.02 | F37: Ressarcimento 40% Art.22-A | G37: 23661.94 | H37: =G37 -> 23661.94
C38: 3.33.90.93.02 | F38: Ressarcimento 30%, Art. 22-B, MP 03/2024. | G38: 25229.93 | H38: =G38 -> 25229.93
C39: 3.31.90.13.02 | F39: Salário Maternidade INSS RGPS | G39: 0 | H39: =G39 -> 0
C40: 3.31.90.13.02 | F40: Salário família INSS RGPS | G40: 0 | H40: =G40 -> 0
C41: 3.31.90.92.11 | F41: Venc. P. Civil (Exerc. Anterior) DEA | G41: 0 | H41: 0
C42: 3.3.90.46.00 | D42: 3645 | F42: Auxílio-Alimentação RGPS | G42: 1000 | H42: =G42 -> 1000 | I42: 0 | L42: =H44-257926.4 -> 0
C43: 3.31.90.94.01 | F43: Vencimento P. Civil (indenizações) folha banco | G43: 49891.87 | H43: =G43 -> 49891.87
B44: _ | C44: _ | D44: 211.110.10X | E44: 111111901 | H44: 257926.4 | I44: =SUM(I33:I43) -> 15363.42
D45: MILITAR
A46: EVENTO | B46: NE | C46: NATUREZA | D46: CLASSIFICAÇÃO DA LIQUIDAÇÃO | E46: CLASSIFICAÇÃO PAGAMENTO | F46: DESCRIÇÃO | G46: LÍQUIDO | H46: LIQUIDAÇÃO | I46: IRRF
C47: 3.31.90.12.43 | F47: 13° Salário Miliar RPPS | G47: 48.44 | H47: =G47 -> 48.44 | I47: 0
C48: 3.31.90.12.45 | F48: Férias Abono Const. Militar RPPS | G48: 17.98 | H48: =G48 -> 17.98 | I48: 0
C49: 3.31.90.12.01 | F49: SOLDO PESSOAL MILITAR RPPS folha banco | G49: 11569.55 | H49: =G49-H47-H53-H48-H54-H51-H56-H52 -> 7713.54 | I49: 4320.57
G50: 0 | H50: 0
C51: 3.33.90.93.02 | F51: Ressarcimento 40% Art.22-A | G51: 3789.59 | H51: =G51 -> 3789.59
C52: 3.33.90.93.02 | F52: AUXILIO FARDAMENTO PESSOAL MILIAR | G52: 0 | H52: =G52 -> 0
C53: 3.33.90.93 | F53: indenização hórario extr. | G53: 0 | H53: =G53 -> 0
C54: 3.31.90.13.02 | F54: Salário família INSS | G54: 0 | H54: =G54 -> 0
C55: 3.31.90.92.12 | D55: NÃO EXIGE | F55: Venc. P. Civil (Exerc. Anterior) DEA folha banco | G55: 561.11 | H55: =G55 -> 561.11
C56: 3.3.90.46.00 | D56: NÃO EXIGE | F56: Auxílio-Alimentação RGPS | G56: 0 | H56: =G56 -> 0 | I56: 0
C57: 3.31.90.94.01 | D57: NÃO EXIGE | F57: Vencimento P. Civil (indenizações) folha banco | G57: 3789.59 | H57: =G57 -> 3789.59
B58: _ | C58: _ | D58: 211.110.10X | E58: 111111901 | H58: 15920.25 | I58: =SUM(I47:I57) -> 4320.57
E61: IRRF
C62: 211110101 | D62: =H6+H8+H11+H14+H26+H27+H28+H35+H39+H41+H43+H10+H18+H40 -> 302750.66 | E62: =I15+I30+I44 -> 37317.51 | F62: =D62+E62 -> 340068.17 | I62: =H15+H30+H44+H58 -> 471029.4
C63: 211110102 | D63: =G7+G19+G33 -> 50739.25
C64: 211110103 | D64: =G9+G22+G34 -> 113.59 | F64: =D65+E62 -> 390921.01
D65: =SUM(D62:D64) -> 353603.5 | E65: =D65-I62 -> -117425.9
F66: GABINETE
F67: 590184.78 | G67: VALOR DO ORGÃO PARA EMPENHO
A68: OBS: Para calcular o valor da FOPAG Valor do Orgão para empenho (+) encargos sociais | F68: 24685.86 | G68: FUNDO FINANCEIRO
B69: (RESUMO GERAL) | F69: 4503.31 | G69: FUNDO PREVIDENCIÁRIO
F70: 68775.92 | G70: INSS
F71: 6257.76 | G71: PLANSAUDE
F72: 0 | G72: PLANSAUDE NÃO CONSTANTE NO RESUMO
F73: 0 | G73: GURUPI PREV
F74: 0 | G74: PREVIPALMAS REQUISITADO
F75: 0 | G75: FUNDO DE PREVIDÊNCIA MILITAR
F76: 0 | G76: INSTITUTO DE SEG. MUNICIPAL DE GOIÁS
B77: TOTAL DA FOLHA | F77: =SUM(F67:F76) -> 694407.63
B78: REDUTOR CONSTITUCIONAL | F78: 0
E79: VALOR DA FOPAG | F79: =F77-F78 -> 694407.63
B80: LIQUIDAÇÃO DA FOLHA DE PAGAMENTO (BANCOS)
A82: PD BANCO DO BRASIL | D82: =F91 -> 386416.43
A83: CNPJ: 01.786.029/0001-03
A84: TOTAL GERAL R$
A86: OBS: Para calcular o valor do Banco do Brasil (resumo do ativo) | F86: GABINETE
B87: Valor do banco | F87: =H30+H44 -> 386416.43
B88: MENOS | F88: =H8+H10+H18+H39+H40 -> 0
B89: Salário Familia + Salario Maternidade INSS
F91: =F87-(F88+F89) -> 386416.43

Sheet CONSIGNAÇÕES FOLHA 1
B1: FOPAG DO MÊS DE MAIO/2026 - 1
A3: LÍQUIDO DOS CONTRATOS | D3: 68692.72
A4: LÍQUIDO VENCIMENTO PESSOAL CIVIL RPPS | D4: 128490.03
A5: LÍQUIDO DO SUBSÍDIO RGPS | D5: 257926.4
A6: LIQUIDO PESSOAL MILITAR | D6: 15920.25
A7: VALOR TOTAL DO LÍQUIDO | D7: =SUM(D3:D6) -> 471029.4
A11: CONSIGNAÇÕES FOPAG
F12: 31.90.11.01 | G12: 31.90.11.74 (311.210.131) | H12: 31.90.12.01
B13: INSC. EVEN | C13: BANCO | D13: ITEM PATR. | E13: DESCRIÇÃO | F13: CIVIL RPPS | G13: CIVIL RGPS | H13: MILITAR | I13: PD (RPPS) | J13: PD (RGPS)
B14: 25.091.307/0001-76 | D14: 164 | E14: FUNDO DE PREVIDÊNCIA (FUNDO FINANCEIRO) | F14: 9341.69 | G14: 0 | H14: 2421.75
B15: 25.091.307/0001-76 | D15: 164 | E15: FUNDO DE PREVIDÊNCIA - FDO FINANCEIRO (31.90.92) DEA | F15: 624.12 | G15: 0 | H15: 70.62
B16: 25.091.307/0001-76 | D16: 70 | E16: FUNDO PREVIDÊNCIARIO segurado | F16: 3019.16 | G16: 0
B17: 25.091.307/0001-76 | D17: 70 | E17: FUNDO PREVIDÊNCIARIO (31.90.92) DEA | F17: 85.86 | G17: 0
B18: 00.394.460.0058-87 | C18: CODIGO DE BARRAS | D18: 105 | E18: INSS | F18: 0 | G18: 22841.36
B19: 00.394.460.0058-87 | C19: CODIGO DE BARRAS | D19: 105 | E19: INSS (92) DEA | G19: 0
B20: 01.786.029/0001-03 | E20: IRRF | F20: 21954.09 | G20: 15363.42 | H20: 4320.57
B21: 14.120.591/0001-45 | C21: 104, AG:0793; CC:0060006019 | D21: 189 | E21: PREV REQU (MUNICIPIO GURUPI - MANTIS) | F21: 0 | G21: 0
B22: 08.948.407/0001-57 | C22: 001, AG:00868, CC:158526 | D22: 102 | E22: INSTITUTO DE SEG. MUNICIPAL DE GOIÁS | F22: 0 | G22: 0
B23: 08.948.407/0001-57 | C23: 001, AG:00868, CC:158526 | D23: 102 | E23: INSTITUTO DE SEG. MUNICIPAL DE GOIÁS (31.90.92) DEA | F23: 0 | G23: 0
B24: 05.278.848/0001-09 | C24: 104, AG: 40657, CC: 060020073 | D24: 189 | E24: PREVIPALMAS REQUISITADO | F24: 0 | G24: 0
B25: 25.053.190/0001-36 | C25: BOLETO JUDICIAL | D25: 84 | E25: Desconto Judicial (TJTO) | F25: 0 | G25: 0
B26: 03.903.286/0001-03 | C26: 001, AG:15059, CC: 806145 | D26: 90 | E26: PLANO DE SAÚDE/PM/ MENS. /COMPART. | F26: 0 | G26: 0 | H26: =864.91+1229.21+119.92 -> 2214.04
B27: 17.327894/0001-21 | C27: 070, AG:380, CC: 0003800264961 | D27: 82 | E27: PLANSAÚDE COMPARTICIPAÇÃO | F27: 654 | G27: 888 | H27: 864.91
B28: 17.327894/0001-21 | C28: 070, AG:380, CC: 0003800264961 | D28: 83 | E28: PLANSAÚDE DEPEND. INDIRETO | F28: 0 | G28: 671.79 | H28: 0
B29: 17.327894/0001-21 | C29: 070, AG:380, CC: 0003800264961 | D29: 96 | E29: PLANSAÚDE – PARCELAMENTO | F29: 0 | G29: 0 | H29: 0
B30: 17.327894/0001-21 | C30: 070, AG:380, CC: 0003800264961 | D30: 81 | E30: PLANSAÚDE TAXA DE INSC. | F30: 0 | G30: 0 | H30: 0
B31: 38.137.329/0001-71 | C31: 001, AG: 1505, CC: 1325132 | D31: 102 | E31: ASSECAD MENSALIDADE | F31: 345.22 | G31: 49.86 | H31: 86.49
B32: 38.137.329/0001-71 | C32: 001, AG: 1886-4, CC: 325139 | D32: 102 | E32: ASSECAD PARCELAMENTO | F32: 0 | G32: 0 | H32: 0
B33: 38.137.329/0001-71 | C33: 001, AG: 1886-4, CC: 325139 | D33: 102 | E33: ASSECAD COMPARTICIP. | F33: 0 | G33: 0 | H33: 0
B34: 38.137.329/0001-71 | C34: 001, AG: 1886-4, CC: 1325139 | D34: 102 | E34: ASSECAD UNIMED | F34: 0 | G34: 0 | H34: 0
B35: 01.385.752/0001-80 | C35: 001/1505-9/48338-9 | D35: 102 | E35: ASSER-RURALTINS (PLANO DE SAÚDE | F35: 0 | G35: 0 | H35: 0
B36: 26.753.491/0001-35 | C36: 001, AG:1886, CC: 143358 | D36: 102 | E36: ASSINE COMPARTICIPAÇÃO | F36: 0 | G36: 0 | H36: 0
B37: 26.753.491/0001-35 | C37: 001, AG:1886, CC: 143358 | D37: 102 | E37: ASSINE MENSALIDADE | F37: 0 | G37: 0 | H37: 0
B38: 26.753.491/0001-35 | C38: 001, AG:1886, CC: 143358 | D38: 102 | E38: ASSINE PLANO DE SAÚDE | F38: 0 | G38: 0 | H38: 0
B39: 71.027.866.0001-34 | C39: 218, AG:0010 CC:104183 | D39: 102 | E39: Bonsucesso – cartão de credito | F39: 0 | G39: 0 | H39: 0
B40: 71.027.866/0001-34 | C40: 218, AG:0010 CC:104183 | D40: 102 | E40: BANCO BONSUCESSO S/A | F40: 0 | G40: 0
B41: 00.000.000/5099-73 | C41: 001, AG:36153, CC:57940 | D41: 78 | E41: BB CRÉD. FÁCIL (BB CONSIGNAÇÃO) | F41: 4979.09 | G41: 0 | H41: 0
B42: 61.186.680/0001-74 | C42: 341, AG:12480 CC:084061 | D42: 175 | E42: BMG – CARTÃO DE CREDITO | F42: 0 | G42: 0
B43: 61.186.680/0001-74 | C43: 341, AG:12480 CC:084061 | D43: 175 | E43: BMG CONSIGNAÇÃO | F43: 0 | G43: 0
B44: 37.238.516/0001-89 | C44: 001, AG: 1505, CC:0172642 | D44: 102 | E44: SINDEPOL - SIND. DOS DEL. (mensalidade) | F44: 0 | G44: 0
B45: 60.746.948/0001-12 | C45: 237, AG:41300, CC:274348 | D45: 175 | E45: BRADESCO - CONSIGNAÇÕES | F45: 0 | G45: 559
B46: 18.742.418/0001-30 | C46: AG: 5004, CC: 10227784 | D46: 102 | E46: SINFITO | F46: 0 | G46: 0
B47: 02.588.345/0001-33 | C47: 001, AG:36153, CC:804797 | D47: 95 | E47: PRODIVINO EMPRESTIMO | F47: 0 | G47: 558.99
B48: 02.588.345/0001-33 | C48: CC:81.100-9 | D48: 76 | E48: PRODIVINO HABITACIONAL | F48: 0 | G48: 0
B49: 02.889.429/0001-07 | C49: 104/3414/00000416-2 | D49: 102 | E49: SINDIFATO (MENSALIDADE) | F49: 0 | G49: 0
B50: 00.977.970/0001-41 | C50: 001, AG:1505, CC:1483331 | D50: 102 | E50: SINDIFISCAL (MENSALIDADE) | F50: 0 | G50: 0
B51: 24.851.628/0001-69 | C51: 001, AG:1886, CC:1071424 | D51: 102 | E51: SINTRAS MENSALIDADE | F51: 0 | G51: 0
B52: 26.752.436/0001-20 | C52: 748, AG:39830, CC:2135 | D52: 102 | E52: SISEPE MENSALIDADE | F52: 345.22 | G52: 0
B53: 40.083.667/0001-10 | C53: 033,AG: 3717, CC: 130045885 | D53: 175 | E53: CAPITAL CONSIGNAÇÃO | F53: 0 | G53: 0
... B59: 04.114.667/0001-76 | C59: 001, AG: 3962, CC: 53000X | D59: 102 | E59: AGEPOL-TO | F59: 0 | G59: 0
B60: 03.903.286/0001-03 | C60: 748, AG:0911 C/C:00000416045 | D60: 91 | E60: FAS-POLÍCIA MILITAR | F60: 0 | G60: 0 | H60: 89.1
B61: 22.328.661/0001-83 | C61: 001, AG:3962, CC:000000383139 | D61: 102 | E61: ASPA- POLICIA CIVIL | F61: 0 | G61: 0
B62: 07.799.277/0001-75 | C62: 237 AG:3090 CC:14540 | D62: 175 | E62: VALOR FINANCIAMENTOS CONSIG | F62: 0 | G62: 0
B63: 62.232.889/0001-90 | C63: 707/00019/3003517 | D63: 175 | E63: BANCO DAYCOVAL | F63: 1284.71 | G63: 0
B64: 26.960.328/0001-43 | C64: 756, AG: 0001, CC: 3263000012 | D64: 175 | E64: SICOOB CREDIPAR | F64: 0 | G64: 0
B65: 08.071.645/0001-27 | C65: 033-2271/0130087562 | D65: 175 | E65: CIASPREV ( CARTÃO DE CRÉDITO) | F65: 0 | G65: 0
B66: 08.071.645/0001-27 | C66: 033-2271/0130087562 | D66: 175 | E66: CIASPREV ( EMPRÉSTIMO) | F66: 0 | G66: 0
B67: 08.071.645/0001-27 | C67: 033-2271/0130087562 | D67: 175 | E67: CIASPREV ( MENSALIDADE) | F67: 40 | G67: 0
B68: 03.990.914/0001-35 | C68: 001 AG: 2967 CC 1074636 | D68: 102 | E68: ORALE (ODONTOLÓGICO) | F68: 0 | G68: 0
B69: 03.110.642/0001-31 | C69: 001 AG:3962 CC:1263595 | D69: 102 | E69: UNIÃO DOS MILITARES DO TOCANTINS | G69: 0 | H69: 0
B70: 17.327894/0001-21 | C70: 070, AG:380, CC: 0003800264961 | D70: 80 | E70: PLANSAÚDE MENSALIDADE | F70: 1095.33 | G70: 1533.87 | H70: 1229.21
B71: 17.327894/0001-21 | C71: 070, AG:380, CC: 0003800264961 | D71: 80 | E71: PLANSAÚDE MENSALIDADE (92) DEA | F71: 4.68
B72: 01.786.029/0001-03 | C72: 001 AG:36153, CC:900001 | D72: 74 | E72: PENSÃO ALIMENTÍCIA | F72: 0 | G72: 0
B73: 03.903.286.0001.03 | C73: 748, AG: 0911, C/C 000000416070 | D73: 92 | E73: PECÚLIO POLICIAL MILITAR | F73: 0 | G73: 0 | H73: 157.44
B74: 92.812.098.0001-08 | C74: 001,AG: 10-8, CC: 25977-2 | D74: 175 | E74: FUTURO PREVIDÊNCIA | F74: 0 | G74: 0
B75: 43.299.408/0001-19 | C75: 033, AG: 2271 C/C: 00013011340-7 | D75: 175 | E75: MEUCASHCARD (Cartão Beneficio) | F75: 0 | G75: 0
B76: 33.923.798/0001-00 | C76: 070; AG: 0027; C/C: 00002711305 | D76: 175 | E76: BANCO MASTER (CARTÃO BENÉFICIO + CARTAO CRÉDIO | F76: 0 | G76: 0
B77: 90.400.888/0001-42 | C77: AG: 0725; CC: 290070617 | D77: 175 | E77: SANTANDER/OLÉ | F77: 0 | G77: 0
B78: 55.158.624/0001-23 | C78: 329; AG:0001; C/C. 9895338-2 | D78: 175 | E78: FYDIGITAL (cartão beneficio) | F78: 0 | G78: 0
B79: 39.876.528/0001-64 | C79: 033, AG:2271; C/C. 0000130119850 | E79: CLICLKBANK (CARTÃO BENEFICIO) | F79: 0 | G79: 0
B80: 44.100.799/0001-63 | C80: 403- AG:001 C/C: 3794585-7 | D80: 175 | E80: VEM CARD (CARTÃO BENEFICIO) | F80: 0 | G80: 0
B81: 18.394.228/0001-79 | C81: 077; AG: 0001 C/C: 000145195740 | D81: 175 | E81: CDC SDC CARTÃO DE CREDITO | F81: 0 | G81: 0
B82: 36.583.700/0001-01 | C82: 237, AG:03393 C/C: 0001428-1 | D82: 175 | E82: QISTA S/A | F82: 0 | G82: 0
B83: 20.308.187/0001-00 | C83: 241/0001/49905807 | D83: 175 | E83: AVANCARD | F83: 0 | G83: 0
B84: 29.961.505/0001-02 | C84: 208, AG:0001, C/C. 130119898 | D84: 175 | E84: HOJE PREVIDÊNCIA | F84: 0 | G84: 0
B85: 46.405.997/0001-60 | C85: AG: 0911, CC: 174633 | D85: 102 | E85: AJUSP-TO | F85: 66.78 | G85: 0
B86: 00.000.208.0001/00 | C86: 70, AG: 0027, CC:0000271077018 | D86: 175 | E86: BRB- BANCO BRASILIA/ PASSIVOS | F86: 3144.15 | G86: 2202.56 | H86: 555.13
B87: 00.000.208.0001/00 | C87: 70, AG: 0027, CC:0271077034 | D87: 175 | E87: BRB- BANCO BRASILIA CONSIGNADO | F87: 3024.5 | G87: 2202.56 | H87: 1046.75
B88: 00.000.208.0001/00 | C88: 70, AG: 0027, CC:0270239146 | D88: 175 | E88: BRB AUXÍLIO ALIMENTAÇÃO | F88: 0 | G88: 1000
B89: 39.330.901/00001-87 | C89: 329, AG:00001 C/C: 26070 | D89: 175 | E89: KARD BANK | F89: 0 | G89: 571.79
B90: 56.984.959/00001-63 | C90: 033, AG:3932 C/C: 0000130105733 | D90: 175 | E90: ZAHAV (Adiant.Salário) | F90: 0 | G90: 812.61
B91: 42.095.636/0001-04 | C91: 457, AG:00001 C/C:00007351150 | D91: 175 | E91: WEBCASH (Cartão de Crédito) 3336 | F91: 0
B92: 42.095.636/0001-04 | C92: 457, AG:00001 C/C:00007351150 | D92: 175 | E92: WEBCASH (Adiant. De Salário) 3634 | F92: 0
B93: 42.095.636/0001-04 | C93: 457, AG:00001 C/C:00007351150 | D93: 175 | E93: WEBCASH (Cartão de Crédito) 3634 | F93: 0
B94: 26.960.328/0001-43 | C94: 756, AG: 0001, CC: 3263000012 | D94: 175 | E94: SICOOB PASSIVOS | F94: 0
B95: 01.786.029/0001-03 | C95: 001, AG:36153, CC:6338-X | D95: 175 | E95: BANCO DO BRASIL PASSIVOS | F95: 4979.08 | G95: 0
B96: 59.285.411/0001-13 | C96: 629, AG:00019, CC:28861 | D96: 175 | E96: BANCO PANAMERICANO – PASSIVOS | F96: 0
B97: 17.324.317/0001-86 | C97: 0070: 380: 380.026499-6 | D97: 75 | E97: FUNGERP | F97: 0
A98: VALOR TOTAL DAS CONMSIGNAÇÕES | F98: =SUM(F14:F97) -> 57345.57 | G98: =SUM(G14:G95) -> 49255.81 | H98: =SUM(H14:H97) -> 13056.01
B101: 2018NE000 | C101: 3.31.90.11.01 | D101: 311110101 | E101: VENCIMENTO DE PESSOAL CIVIL RPPS | F101: =F98 -> 57345.57
B102: 2018NE000 | C102: 3.31.90.11.74 | D102: 311110131 | E102: SUBSÍDIO CIVIL RPPS | F102: 0 | G102: 0
B103: 2018NE000 | C103: 331.90.04.01 | D103: 311210401 | E103: DESP. REMUNERAÇÃO - CONTRATOS TEMPORÁRIOS - RGPS | F103: =F131 -> 9974.28
B104: 2018NE000 | C104: 3.31.90.11.74 | D104: 311210131 | E104: SUBSÍDIO CIVIL RGPS/ | F104: =G98 -> 49255.81 | G104: 0
B105: 2018NE000 | C105: 3.31.90.92.11 | D105: NÃO EXIGE | E105: PESSOL MILITR RPPS | F105: =H98 -> 13056.01 | G105: 0
D107: APROPRIAÇÃO DAS CONSIGNAÇÕES DOS CONTRATOS - RGPS
A108: CÓDIGO | B108: INSC. EVENTO | C108: BANCO | D108: ITEM PATR. | E108: DESCRIÇÃO | F108: valor R$ | G108: NL | H108: PD (RPPS) | I108: PD (RGPS)
B109: 00.394.460.0058-87 | D109: 105 | E109: INSS | F109: 6747.25
B110: 00.394.460.0058-87 | D110: 105 | E110: INSS (92) DEA | F110: 0
B111: 01.786.029/0001-03 | E111: IRRF | F111: 0
B112: 01.786.029.0001-03 | C112: 001 AG:36153, CC:900001 | D112: 74 | E112: PENSÃO ALIMENTÍCIA | F112: 0 | L112: =F104-46494.27 -> 2761.54
...

Sheet NES
A1: N° NE | B1: NATUREZA | C1: DEZCRIÇÃO DA NATUREZA | D1: SALDO 622.921.001 | E1: FOLHA | F1: VALOR DO REFORÇO R$
A2: 2018NE0000 | B2: 31.90.04.01 | C2: DESPESAS E REMUNERAÇÃO DOS CONTRATOS TEMPORÁRIOS | D2: ='LÍQUIDO FOLHA -1'!H6+'LÍQUIDO FOLHA -1'!H7+'CONSIGNAÇÕES FOLHA 1'!F131 -> 73367 | F2: =D2+E2 -> 73367 | G2: =F2+F4 -> 73367
A3: 2018NE0000 | B3: 31.90.04.02 | C3: 13° SALÁRIO - CONTRATOS TEMPORÁRIOS | F3: =D3 | G3: 0
A4: 2018NE0000 | B4: 31.90.04.45 | C4: FÉRIAS E ABONO DOS CONTRATO TEMP. | D4: ='LÍQUIDO FOLHA -1'!H9 -> 0 | F4: =D4 -> 0 | G4: 0
A5: 2018NE0000 | B5: 31.90.05.07 | C5: SALÁRIO FAMÍLIA CIVIL RPPS | D5: ='LÍQUIDO FOLHA -1'!H18 -> 0 | F5: =D5 -> 0
A6: 2018NE0000 | B6: 31.90.11.01 | C6: VENCIMENTO PESSOAL CIVIL RPPS | D6: ='LÍQUIDO FOLHA -1'!H28+'CONSIGNAÇÕES FOLHA 1'!F98 -> 70249.57 | F6: =D6 -> 70249.57 | G6: =F6+F7+F8+F9 -> 338671.47
A7: 2018NE0000 | B7: 31.90.11.43 | C7: 13° SALÁRIO CIVIL RPPS | D7: ='LÍQUIDO FOLHA -1'!H19+'LÍQUIDO FOLHA -1'!H33 -> 50514.25 | F7: =D7 -> 50514.25 | G7: 0
A8: 2018NE0000 | B8: 31.90.11.45 | C8: FÉRIAS E ABONO CIVIL RPPS | D8: ='LÍQUIDO FOLHA -1'!H22+'LÍQUIDO FOLHA -1'!H34 -> 113.59 | F8: =D8 -> 113.59 | G8: 0
A9: 2018NE0000 | B9: 31.90.11.74 | C9: SUBSÍDIOS CIVIL RGPS | D9: ='LÍQUIDO FOLHA -1'!G27+'LÍQUIDO FOLHA -1'!H35+'CONSIGNAÇÕES FOLHA 1'!G98 -> 217794.06 | F9: =D9 -> 217794.06 | G9: 0
A10: 2018NE0000 | B10: 31.90.13.02 | C10: SALÁRIO MATERNIDADE INSS RGPS | D10: ='LÍQUIDO FOLHA -1'!H8+'LÍQUIDO FOLHA -1'!H10+'LÍQUIDO FOLHA -1'!H39+'LÍQUIDO FOLHA -1'!H40 -> 0 | F10: =D10 -> 0 | G10: 0
A11: 2018NE0000 | B11: 31.90.92.04 | C11: CONTRATOS (DESP. DE EXERCÍCIO ANTERIOR) | D11: ='LÍQUIDO FOLHA -1'!H11 | F11: =D11 | G11: 0
A12: 2018NE0000 | B12: 31.90.92.11 | C12: VENCIMENTO PESSOAL CIVIL (EXERC. ANTERIOR) | D12: ='LÍQUIDO FOLHA -1'!H26+'LÍQUIDO FOLHA -1'!H41 -> 5448.82 | F12: =D12 -> 5448.82 | G12: =F11+F12 -> 5448.82
A13: 2018NE0000 | B13: 31.90.92.13 | C13: INSS DE EXERC. ANTERIOR | D13: 0 | F13: =D13 -> 0
A14: 2018NE0000 | B14: 31.90.92.94 | C14: INDENIZAÇÕES E RESTITUIÇÕES | F14: 0 | G14: 0
A15: 2018NE0000 | B15: 31.90.94.01 | C15: VENCIMENTO PESSOAL CIVIL INDENIZAÇÕES | D15: ='LÍQUIDO FOLHA -1'!H14+'LÍQUIDO FOLHA -1'!H29+'LÍQUIDO FOLHA -1'!H43 -> 80698.04 | F15: =D15 -> 80698.04 | G15: =F15 -> 80698.04
A16: 2018NE0000 | B16: 31.90.13.02 | C16: INSS (RGPS) | D16: ='CONSIGNAÇÕES FOLHA 1'!F141 -> 52085.18 | F16: =D16 -> 52085.18 | G16: =F10+F16+F21+F22+F23 -> 56928.68
A17: 2018NE0000 | B17: 31.90.13.99 | C17: OUTRAS OBRIGAÇÕES PATRONAIS | D17: 0 | F17: 0 | G17: 0
A18: 2018NE0000 | B18: 31.91.92.13 | C18: OBRIGAÇÕES PATRONAIS (EXERC. ANTERIOR) | D18: ='CONSIGNAÇÕES FOLHA 1'!F153+'CONSIGNAÇÕES FOLHA 1'!F161 -> 1223.68 | F18: =D18 -> 1223.68 | G18: =F18 -> 1223.68
A19: 2018NE0000 | B19: 31.91.13.01 | C19: CONTRIBUIÇÃO PATRONAL - ATIVO CIVIL | D19: ='CONSIGNAÇÕES FOLHA 1'!F146+'CONSIGNAÇÕES FOLHA 1'!F169 -> 23039.57 | F19: =D19 -> 23039.57 | G19: 0
A20: 2018NE0000 | B20: 31.91.13.03 | C20: PLANSAUDE CONTRIBUIÇÃO PATRONAL | D20: ='CONSIGNAÇÕES FOLHA 1'!F176+'CONSIGNAÇÕES FOLHA 1'!F181 -> 6257.76 | F20: =D20 -> 6257.76 | G20: =F19+F20 -> 29297.33
A21: 2018NE0000 | B21: 31.90.13.14 | C21: PREVI PALMAS REQUISITADO | D21: ='CONSIGNAÇÕES FOLHA 1'!F187 -> 0 | F21: =D21 -> 0 | G21: 0
A22: 2018NE | B22: 31.90.13.14 | C22: PREVI PAR REQUISITADO | D22: ='CONSIGNAÇÕES FOLHA 1'!F196 -> 0 | F22: =D22 -> 0
A23: 2018NE0000 | B23: 31.90.13.40 | C23: FUNDO DE PREV. DE GOIÁS | D23: ='CONSIGNAÇÕES FOLHA 1'!F202 -> 4843.5 | F23: =D23 -> 4843.5 | G23: =SUM(G2:G21) -> 585635.02
F24: =SUM(F2:F23) -> 585635.02 | G24: =F26-G23 -> 108772.61
F26: ='CONSIGNAÇÕES FOLHA 1'!F212 -> 694407.63
F27: =F26-F24 -> 108772.61
F30: =F27-F28 -> 108772.61

Sheet Reconciliacao
A1: SALÁRIOS | B1: DÉCIMO TERCEIRO | C1: FÉRIAS
B2: =B11+B14 -> 50739.25 | C2: =B10+B15 -> 113.59
A4: =B21-B4-C4 -> 250058.79 | B4: =SUM(B2) -> 50739.25 | C4: =SUM(C2) -> 113.59 | D4: =A4+B4+C4 -> 300911.63
A6: 211.110.101 | B6: 211.110.102 | C6: 211.110.103
C8: PENSÃO ALIMENTÍCIA
A9: 31.90.04.01 | B9: ='LÍQUIDO FOLHA -1'!H6 -> 63167.72 | C9: ='CONSIGNAÇÕES FOLHA 1'!F112 -> 0 | D9: =B9+C9 -> 63167.72
A10: 31.90.04.45 | B10: ='LÍQUIDO FOLHA -1'!H9 -> 0 | D10: =B10+C10 -> 0
A11: 31.90.04.02 | B11: ='LÍQUIDO FOLHA -1'!H7 -> 225 | D11: =B11+C11 -> 225
A12: 31.90.13.02 | B12: ='LÍQUIDO FOLHA -1'!H8+'LÍQUIDO FOLHA -1'!H10+'LÍQUIDO FOLHA -1'!H39+'LÍQUIDO FOLHA -1'!H40 -> 0 | D12: =B12+C12 -> 0
A13: 31.90.05.07 | B13: ='LÍQUIDO FOLHA -1'!H18 -> 0 | D13: =B13+C13 -> 0
A14: 31.90.11.43 | B14: ='LÍQUIDO FOLHA -1'!H19+'LÍQUIDO FOLHA -1'!H33 -> 50514.25 | D14: =B14+C14 -> 50514.25
A15: 31.90.11.45 | B15: ='LÍQUIDO FOLHA -1'!H22+'LÍQUIDO FOLHA -1'!H34 -> 113.59 | D15: =B15+C15 -> 113.59
A16: 31.90.11.01 | B16: ='LÍQUIDO FOLHA -1'!H28+'LÍQUIDO FOLHA -1'!H36 -> 12904 | C16: ='CONSIGNAÇÕES FOLHA 1'!F72 -> 0 | D16: =B16+C16 -> 12904
A17: 31.90.94.01 | D17: =B17+C17 -> 0
A18: 31.90.11.74 | B18: ='LÍQUIDO FOLHA -1'!H27+'LÍQUIDO FOLHA -1'!H35 -> 168538.25 | C18: ='CONSIGNAÇÕES FOLHA 1'!G72 -> 0 | D18: =B18+C18 -> 168538.25
A19: 31.90.92.11 | B19: ='LÍQUIDO FOLHA -1'!H41+'LÍQUIDO FOLHA -1'!H26 -> 5448.82 | C19: 0 | D19: =B19+C19 -> 5448.82
A20: 31.90.92.04 | B20: ='LÍQUIDO FOLHA -1'!H11 | D20: =B20+C20 -> 0
B21: =SUM(B9:B20) -> 300911.63 | C21: =SUM(C9:C19) -> 0 | D21: =SUM(D9:D20) -> 300911.63
A22: VALOR REAL | B22: ='LÍQUIDO FOLHA -1'!I62 -> 471029.4
A23: DIFERNÇA | B23: =B22-B21 -> 170117.77

Sheet Cruzamento Rubricas
A1: 31.90.04 | B1: 31.90.13 | C1: 31.90.94 | D1: 31.90.12 | E1: 31.90.11 | F1: 31.90.11.74 | G1: 31.90.11.43 | H1: 31.90.11.45 | I1: 31.90.11.07 | J1: 33.90.08 | K1: 31.91.13.01 | L1: 33.90.93. 40% | M1: 33.90.93. 30% | N1: 33.90.46 | O1: 31.91.13.03
A2: ='LÍQUIDO FOLHA -1'!H6 -> 63167.72 | B2: ='CONSIGNAÇÕES FOLHA 1'!F141 -> 52085.18 | C2: ='LÍQUIDO FOLHA -1'!H14 -> 2800 | D2: ='LÍQUIDO FOLHA -1'!H49 -> 7713.54 | E2: ='LÍQUIDO FOLHA -1'!H28 -> 12904 | F2: ='LÍQUIDO FOLHA -1'!H27 -> 28173.56 | G2: ='LÍQUIDO FOLHA -1'!H19 -> 32736.28 | H2: ='LÍQUIDO FOLHA -1'!H22 -> 113.59 | I2: ='LÍQUIDO FOLHA -1'!G20 -> 0 | J2: ='LÍQUIDO FOLHA -1'!H52 -> 0 | K2: ='CONSIGNAÇÕES FOLHA 1'!F146 -> 18683.37 | L2: ='LÍQUIDO FOLHA -1'!H25 -> 15935.28 | M2: ='LÍQUIDO FOLHA -1'!H24 -> 5172.33 | N2: ='LÍQUIDO FOLHA -1'!H23 -> 0 | O2: ='CONSIGNAÇÕES FOLHA 1'!F176 -> 6257.76
A3: ='LÍQUIDO FOLHA -1'!H7 -> 225 | B3: ='LÍQUIDO FOLHA -1'!H39 -> 0 | C3: ='LÍQUIDO FOLHA -1'!H29 -> 28006.17 | D3: ='CONSIGNAÇÕES FOLHA 1'!H98 -> 13056.01 | E3: ='CONSIGNAÇÕES FOLHA 1'!F98 -> 57345.57 | F3: ='LÍQUIDO FOLHA -1'!H35 -> 140364.69 | G3: ='LÍQUIDO FOLHA -1'!H33 -> 17777.97 | H3: ='LÍQUIDO FOLHA -1'!G34 -> 0 | I3: ='LÍQUIDO FOLHA -1'!H21 -> 0 | K3: ='CONSIGNAÇÕES FOLHA 1'!F169 -> 4356.2 | L3: ='LÍQUIDO FOLHA -1'!H37 -> 23661.94 | M3: ='LÍQUIDO FOLHA -1'!H38 -> 25229.93 | N3: ='LÍQUIDO FOLHA -1'!H42 -> 1000 | O3: ='CONSIGNAÇÕES FOLHA 1'!F181 -> 0
A4: ='LÍQUIDO FOLHA -1'!G10 -> 0 | B4: ='LÍQUIDO FOLHA -1'!H40 -> 0 | C4: ='LÍQUIDO FOLHA -1'!H43 -> 49891.87 | E4: 0 | F4: ='CONSIGNAÇÕES FOLHA 1'!G98 -> 49255.81 | G4: ='LÍQUIDO FOLHA -1'!H47 -> 48.44 | H4: ='LÍQUIDO FOLHA -1'!H48 -> 17.98 | I4: =SUM(I2:I3) -> 0 | J4: =SUM(J2:J3) -> 0 | K4: ='CONSIGNAÇÕES FOLHA 1'!F202 -> 4843.5 | L4: ='LÍQUIDO FOLHA -1'!H51 -> 3789.59 | M4: 0 | N4: ='LÍQUIDO FOLHA -1'!H12 -> 2500 | O4: 0
A5: ='CONSIGNAÇÕES FOLHA 1'!F139 -> 16690.74 | B5: ='CONSIGNAÇÕES FOLHA 1'!F187 -> 0 | C5: ='LÍQUIDO FOLHA -1'!H57 -> 3789.59
A6: ='CONSIGNAÇÕES FOLHA 1'!F131 -> 9974.28 | B6: ='CONSIGNAÇÕES FOLHA 1'!F196 -> 0 | C6: 0 | E6: 0 | F6: 0 | G6: 0 | H6: 0 | K6: 0 | O6: =SUM(O2:O4) -> 6257.76
A7: ='LÍQUIDO FOLHA -1'!G9 -> 0
A8: ='LÍQUIDO FOLHA -1'!G8 -> 0 | C8: =SUM(C2:C6) -> 84487.63 | D8: =SUM(D2:D7) -> 20769.55 | E8: =SUM(E2:E6) -> 70249.57 | F8: =SUM(F2:F6) -> 217794.06 | G8: =SUM(G2:G6) -> 50562.69 | H8: =SUM(H2:H6) -> 131.57 | K8: =SUM(K2:K6) -> 27883.07 | L8: =SUM(L2:L6) -> 43386.81 | M8: =SUM(M2:M7) -> 30402.26 | N8: =SUM(N2:N7) -> 3500
A9: =SUM(A2:A8) -> 90057.74
B10: =SUM(B2:B9) -> 52085.18 | G10: =G8-G4 -> 50514.25
K11: NAT- 31.91.13 | L11: =K8+O6 -> 34140.83
A12: =A9-A5 -> 73367 | E12: =E8+F8+G8+H8+I4 -> 338737.89 | K12: NAT.31.90.93 | L12: =L2+L3+M2+M3+M5+L4 -> 73789.07
A13: =A12-225 -> 73142 | B13: 13º 225
P16: =4*180000 -> 720000
E17: D E A | F17: D E A
A18: ='LÍQUIDO FOLHA -1'!F79 -> 694407.63 | B18: =A9+B10+C8+D8+E12+J4+K8+L8+M8+N8+O6+E24+F24 -> 704883.91 | C18: =C16-C17 -> 0 | E18: 31.90.92 | F18: 31.91.92 | K18: =E12-I21-G4-H4 -> 338671.47
B19: =A18-B18 -> -10476.28 | E19: ='LÍQUIDO FOLHA -1'!G41 -> 0 | F19: ='CONSIGNAÇÕES FOLHA 1'!F153 -> 1076.57 | L19: =L8+M8 -> 73789.07 | N19: =K8+O6 -> 34140.83
E20: ='LÍQUIDO FOLHA -1'!H26 -> 5448.82 | F20: ='CONSIGNAÇÕES FOLHA 1'!F161 -> 147.11 | H20: FUNDO | L20: =L19+N8+J4 -> 77289.07
E21: ='CONSIGNAÇÕES FOLHA 1'!F140 -> 0 | H21: PLANSAUDE
E22: ='LÍQUIDO FOLHA -1'!H55 -> 561.11 | F22: ='CONSIGNAÇÕES FOLHA 1'!F208 -> 82.41
E23: 0 | F23: 0
E24: =E19+E20+E21+E22 -> 6009.93 | F24: =SUM(F19:F23) -> 1306.09 | K24: =K2+K3 -> 23039.57 | L24: VENCIMENTOS | M24: SUBSIDIO
L25: =E8-624.12-85.86 -> 69539.59 | M25: =F3+F4 -> 189620.5
E44: =C41+E21 -> 0

Sheet Detalhe Consignacoes
A1: CONSIGNAÇÕES | B1: VALOR | C1: FUNGERP | D1: TOTAL GERAL | E1: BC
A2: SIND FISCAL | D2: ='CONSIGNAÇÕES FOLHA 1'!F50 -> 0 | E2: 0 | F2: =D2-E2 -> 0
A3: santander | D3: ='CONSIGNAÇÕES FOLHA 1'!F77 -> 0 | E3: 0.35 | F3: =D3-E3 -> -0.35
A4: sinfito | D4: ='CONSIGNAÇÕES FOLHA 1'!F55 -> 0 | E4: 0.34 | F4: =D4-E4 -> -0.34
A5: ASSECAD MENS | D5: ='CONSIGNAÇÕES FOLHA 1'!F31 -> 345.22 | E5: 3.74 | F5: =D5-E5 -> 341.48
A6: MEU CASH CARD | D6: ='CONSIGNAÇÕES FOLHA 1'!F75 -> 0 | E6: 1.45 | F6: =D6-E6 -> -1.45
A7: SICOOB PASSIVOS | D7: ='CONSIGNAÇÕES FOLHA 1'!F94 -> 0 | E7: 2.55 | F7: =D7-E7 -> -2.55 | G7: =F7+F8 -> -2.55 | H7: =E7+E8 -> 2.55
A8: SICOOB | D8: ='CONSIGNAÇÕES FOLHA 1'!F64 -> 0 | E8: 0 | F8: =D8-E8 -> 0 | G8: =C6+C7+C8 -> 0
A9: BB CRÉDITO FÁCIL | D9: ='CONSIGNAÇÕES FOLHA 1'!F41 -> 4979.09 | E9: 389.64 | F9: =D9-E9 -> 4589.45 | G9: =F9+F10 -> 9562.99 | H9: =E9+E10 -> 395.18
A10: bb passivos | D10: ='CONSIGNAÇÕES FOLHA 1'!F95 -> 4979.08 | E10: 5.54 | F10: =D10-E10 -> 4973.54
A11: BRADESCO EMPRÉSTIMO | D11: ='CONSIGNAÇÕES FOLHA 1'!F45 -> 0 | E11: 27.74 | F11: =D11-E11 -> -27.74
A12: PANAMERICANO | D12: ='CONSIGNAÇÕES FOLHA 1'!F96 -> 0 | E12: 12.16 | F12: =D12-E12 -> -12.16
A13: FUTURO PREVI | D13: ='CONSIGNAÇÕES FOLHA 1'!F74 -> 0 | E13: 3.95 | F13: =D13-E13 -> -3.95
A14: SISEPE | D14: ='CONSIGNAÇÕES FOLHA 1'!F52 -> 345.22 | E14: 6.17 | F14: =D14-E14 -> 339.05
A15: AGEPOL-TO | D15: ='CONSIGNAÇÕES FOLHA 1'!F59 -> 0 | E15: 0 | F15: =D15-E15 -> 0
A16: SINDEPOL | D16: ='CONSIGNAÇÕES FOLHA 1'!F44 -> 0 | E16: 1.9 | F16: =D16-E16 -> -1.9
A17: SINPOL | D17: ='CONSIGNAÇÕES FOLHA 1'!F58 -> 253.61 | E17: 1.21 | F17: =D17-E17 -> 252.4
A18: SINTRAS | D18: ='CONSIGNAÇÕES FOLHA 1'!F51 -> 0 | E18: 1.1 | F18: =D18-E18 -> -1.1
A19: SEET | D19: ='CONSIGNAÇÕES FOLHA 1'!F57 -> 0 | E19: 1.33 | F19: =D19-E19 -> -1.33
A20: QISTA S/A | D20: ='CONSIGNAÇÕES FOLHA 1'!F82 -> 0 | E20: 4.15 | F20: =D20-E20 -> -4.15
A21: CLICKBANK | D21: ='CONSIGNAÇÕES FOLHA 1'!F79 -> 0 | E21: 0 | F21: =D21-E21 -> 0
A22: CAIXA | D22: ='CONSIGNAÇÕES FOLHA 1'!F56 -> 2104.28 | E22: 124.23 | F22: =D22-E22 -> 1980.05
A23: AJUP | D23: ='CONSIGNAÇÕES FOLHA 1'!F85 -> 66.78 | E23: 0.87 | F23: =D23-E23 -> 65.91
A24: CAPIT CONSIG | D24: ='CONSIGNAÇÕES FOLHA 1'!F53 -> 0 | E24: 11.36 | F24: =D24-E24 -> -11.36
A25: PECULIO UNIÃO | D25: ='CONSIGNAÇÕES FOLHA 1'!F84 -> 0 | E25: 33.32 | F25: =D25-E25 -> -33.32
A26: vem card | D26: ='CONSIGNAÇÕES FOLHA 1'!F80 -> 0 | E26: 1.11 | F26: =D26-E26 -> -1.11
A27: BRB - BANCO BRASILIA | D27: ='CONSIGNAÇÕES FOLHA 1'!F87 -> 3024.5 | E27: 0 | F27: =D27-E27 -> 3024.5
A28: BANCO DAYCOVAL | D28: ='CONSIGNAÇÕES FOLHA 1'!F63 -> 1284.71 | E28: 24.31 | F28: =D28-E28 -> 1260.4
A29: BCO INDUSTRIAL | D29: ='CONSIGNAÇÕES FOLHA 1'!F54 -> 0 | E29: 14.32 | F29: =D29-E29 -> -14.32
A30: CIASPREV | D30: ='CONSIGNAÇÕES FOLHA 1'!F65 -> 0 | E30: 22.08 | F30: =D30-E30 -> -22.08 | G30: =F30+F31+F32 -> -29.43 | H30: =E30+E31+E32 -> 69.43
A31: CIASPREV | D31: ='CONSIGNAÇÕES FOLHA 1'!F66 -> 0 | E31: 44.6 | F31: =D31-E31 -> -44.6
A32: CIASPREV | D32: ='CONSIGNAÇÕES FOLHA 1'!F67 -> 40 | E32: 2.75 | F32: =D32-E32 -> 37.25 | G32: =C30+C31+C32 -> 0
A33: AVANCARD | D33: ='CONSIGNAÇÕES FOLHA 1'!F83 -> 0 | E33: 0 | F33: =D33-E33 -> 0
A34: webcash - 3336 | D34: ='CONSIGNAÇÕES FOLHA 1'!F91 -> 0 | E34: 1.21 | F34: =D34-E34 -> -1.21 | G34: =F34+F35+F36 -> -1.21
A35: webcash - 3634 | D35: ='CONSIGNAÇÕES FOLHA 1'!F92 -> 0 | E35: 0 | F35: =D35-E35 -> 0
A36: webcash - 3634 | D36: ='CONSIGNAÇÕES FOLHA 1'!F93 -> 0 | E36: 0 | F36: =D36-E36 -> 0
A37: BRB -PASSIVOS | D37: ='CONSIGNAÇÕES FOLHA 1'!F86 -> 3144.15 | E37: 194.53 | F37: =D37-E37 -> 2949.62 | G37: =F37+F27 -> 5974.12 | H37: =E27+E37 -> 194.53
C38: =SUM(C2:C37) -> 0 | E38: =SUM(E2:E37) -> 938.01
A42: RGPS | B42: VALOR | C42: FUNGERP | D42: TOTAL GERAL
A43: ASSECAD | B43: ='CONSIGNAÇÕES FOLHA 1'!G31 -> 49.86 | C43: 1.49 | D43: =B43-C43 -> 48.37
A44: CDC SDC CARTÃO DE CREDITO | B44: 273.65 | C44: 4.1 | D44: =B44-C44 -> 269.55
A45: sisepe | B45: ='CONSIGNAÇÕES FOLHA 1'!G52 -> 0 | C45: 0.44 | D45: =B45-C45 -> -0.44
A46: CAIXA TRABALHADOR | B46: ='CONSIGNAÇÕES FOLHA 1'!G56 -> 0 | C46: 17.58 | D46: =B46-C46 -> -17.58
A47: VALOR FINANCIAMENTOS | B47: ='CONSIGNAÇÕES FOLHA 1'!G62 -> 0 | C47: 36.84 | D47: =B47-C47 -> -36.84
A48: SINTRAS | B48: ='CONSIGNAÇÕES FOLHA 1'!G51 -> 0 | C48: 0.47 | D48: =B48-C48 -> -0.47
A49: VEM CARD | B49: ='CONSIGNAÇÕES FOLHA 1'!G80 -> 0 | C49: 13.03 | D49: =B49-C49 -> -13.03
A50: futuro | B50: ='CONSIGNAÇÕES FOLHA 1'!G74 -> 0 | C50: 26.53 | D50: =B50-C50 -> -26.53
A51: BANCO DO BRASIL | B51: ='CONSIGNAÇÕES FOLHA 1'!G41 -> 0 | C51: 113.32 | D51: =B51-C51 -> -113.32
A52: brb | B52: ='CONSIGNAÇÕES FOLHA 1'!G87 -> 2202.56 | C52: 0 | D52: =B52-C52 -> 2202.56
A53: HOJE PREVIDÊNCIA | B53: ='CONSIGNAÇÕES FOLHA 1'!G84 -> 0 | C53: 7.5 | D53: =B53-C53 -> -7.5
A54: banco santander | B54: ='CONSIGNAÇÕES FOLHA 1'!G77 -> 0 | C54: 3.75 | D54: =B54-C54 -> -3.75
A55: banco master | B55: ='CONSIGNAÇÕES FOLHA 1'!G76 -> 0 | C55: 1.99 | D55: =B55-C55 -> -1.99
A56: Bradesco | B56: ='CONSIGNAÇÕES FOLHA 1'!G45 -> 559 | C56: 62.07 | D56: =B56-C56 -> 496.93
A57: RCCARD | B57: ='CONSIGNAÇÕES FOLHA 1'!G81 -> 0 | C57: 0 | D57: =B57-C57 -> 0
C58: =SUM(C43:C57) -> 289.11
A60: ASSECAD | B60: ='CONSIGNAÇÕES FOLHA 1'!F114 -> 0 | C60: 2.17 | D60: =B60-C60 -> -2.17
A61: SINTRAS | B61: ='CONSIGNAÇÕES FOLHA 1'!F115 -> 0 | C61: 0.34 | D61: =B61-C61 -> -0.34
A62: VALOR | B62: ='CONSIGNAÇÕES FOLHA 1'!F118 -> 0 | C62: 44.68 | D62: =B62-C62 -> -44.68
A63: SINFITO | B63: ='CONSIGNAÇÕES FOLHA 1'!F116 -> 0 | C63: 0.22 | D63: =B63-C63 -> -0.22
A64: BANCO DAYCOVAL | B64: ='CONSIGNAÇÕES FOLHA 1'!F121 -> 0 | C64: 43.35 | D64: =B64-C64 -> -43.35
A65: SISEPE | B65: ='CONSIGNAÇÕES FOLHA 1'!F117 -> 0 | C65: 0.2 | D65: =B65-C65 -> -0.2
A66: BRADESC0 | B66: ='CONSIGNAÇÕES FOLHA 1'!F124 -> 0 | C66: 48.03 | D66: =B66-C66 -> -48.03
A67: FUTURO | B67: 618.35 | C67: 9.27 | D67: =B67-C67 -> 609.08
C68: =SUM(C60:C67) -> 148.26

Sheet Listas
A1: Naturezas (Liquido Folha) | B1: Bancos/Instituicoes (Consignacoes)
A2: 3.31.90.04.01 | B2: FUNDO DE PREVIDÊNCIA (FUNDO FINANCEIRO)
A3: 3.31.90.04.02 | B3: FUNDO DE PREVIDÊNCIA - FDO FINANCEIRO (31.90.92) DEA
A4: 3.31.90.13.02 | B4: FUNDO PREVIDÊNCIARIO segurado
A5: 3.31.90.04.45 | B5: FUNDO PREVIDÊNCIARIO (31.90.92) DEA
A6: 3.31.90.92.04 | B6: INSS
A7: 3.33.90.46 | B7: INSS (92) DEA
A8: 33.90.92 | B8: IRRF
A9: 3.31.90.94.01 | B9: PREV REQU (MUNICIPIO GURUPI - MANTIS)
A10: 3.31.90.05.07 | B10: INSTITUTO DE SEG. MUNICIPAL DE GOIÁS
A11: 3.31.90.11.43 | B11: INSTITUTO DE SEG. MUNICIPAL DE GOIÁS (31.90.92) DEA
A12: 31.90.11.07 | B12: PREVIPALMAS REQUISITADO
... A23: 3.31.90.92.12 | B23: ASSER-RURALTINS (PLANO DE SAÚDE
B24: ASSINE COMPARTICIPAÇÃO
B25: ASSINE MENSALIDADE
B26: ASSINE PLANO DE SAÚDE
B27: Bonsucesso – cartão de credito
B28: BANCO BONSUCESSO S/A
B29: BB CRÉD. FÁCIL (BB CONSIGNAÇÃO)
B30: BMG – CARTÃO DE CREDITO
B31: BMG CONSIGNAÇÃO
B32: SINDEPOL - SIND. DOS DEL. (mensalidade)
B33: BRADESCO - CONSIGNAÇÕES
B34: SINFITO
B35: PRODIVINO EMPRESTIMO
... B84: FUNGERP
